pyelan/__init__.py
pyelan/elanGen.py
pyelan/pyelan.py
pyelan/relPathFix.py
pyelan/templates/480.mp4
pyelan/templates/__init__.py
pyelan/templates/elanSkeleton.eaf
pyelan/tests/Letters.eaf
pyelan/tests/__init__.py
pyelan/tests/test_elanGen.py
pyelan-0.1.2.dist-info/LICENSE
pyelan-0.1.2.dist-info/METADATA
pyelan-0.1.2.dist-info/WHEEL
pyelan-0.1.2.dist-info/RECORD
