Metadata-Version: 2.1
Name: pyelan
Version: 0.1.2
Summary: 
Author: Jonathan Keane
Author-email: jkeane@gmail.com
Requires-Python: >=3.8,<4.0
Classifier: Programming Language :: Python :: 3
Classifier: Programming Language :: Python :: 3.8
Classifier: Programming Language :: Python :: 3.9
Classifier: Programming Language :: Python :: 3.10
Classifier: Programming Language :: Python :: 3.11
Classifier: Programming Language :: Python :: 3.12
Requires-Dist: pytest (>=7.4.3,<8.0.0)
